{"id":1328483264,"name":"Test","node_id":"WFR_kwLOA_1uaM5PLwvA","head_branch":"2.36-DHIS2-11541-2","head_sha":"6fca9345876cb9ba1ad8030e5ea4146b16e9b69b","run_number":9908,"event":"pull_request","status":"completed","conclusion":"success","workflow_id":10954,"check_suite_id":4016794074,"check_suite_node_id":"CS_kwDOA_1uaM7va2na","url":"https://api.github.com/repos/dhis2/dhis2-core/actions/runs/1328483264","html_url":"https://github.com/dhis2/dhis2-core/actions/runs/1328483264","pull_requests":[],"created_at":"2021-10-11T10:08:11Z","updated_at":"2021-10-11T10:28:54Z","run_attempt":1,"run_started_at":"2021-10-11T10:08:11Z","jobs_url":"https://api.github.com/repos/dhis2/dhis2-core/actions/runs/1328483264/jobs","logs_url":"https://api.github.com/repos/dhis2/dhis2-core/actions/runs/1328483264/logs","check_suite_url":"https://api.github.com/repos/dhis2/dhis2-core/check-suites/4016794074","artifacts_url":"https://api.github.com/repos/dhis2/dhis2-core/actions/runs/1328483264/artifacts","cancel_url":"https://api.github.com/repos/dhis2/dhis2-core/actions/runs/1328483264/cancel","rerun_url":"https://api.github.com/repos/dhis2/dhis2-core/actions/runs/1328483264/rerun","previous_attempt_url":null,"workflow_url":"https://api.github.com/repos/dhis2/dhis2-core/actions/workflows/10954","head_commit":{"id":"6fca9345876cb9ba1ad8030e5ea4146b16e9b69b","tree_id":"51543d9370cf3e0b87ad8c83824aedb546b76d85","message":"Merge branch '2.36-DHIS2-11541-2' of github.com:dhis2/dhis2-core into 2.36-DHIS2-11541-2","timestamp":"2021-10-11T10:07:55Z","author":{"name":"zubaira","email":"zubair@dhis2.org"},"committer":{"name":"zubaira","email":"zubair@dhis2.org"}},"repository":{"id":66940520,"node_id":"MDEwOlJlcG9zaXRvcnk2Njk0MDUyMA==","name":"dhis2-core","full_name":"dhis2/dhis2-core","private":false,"owner":{"login":"dhis2","id":1089987,"node_id":"MDEyOk9yZ2FuaXphdGlvbjEwODk5ODc=","avatar_url":"https://avatars.githubusercontent.com/u/1089987?v=4","gravatar_id":"","url":"https://api.github.com/users/dhis2","html_url":"https://github.com/dhis2","followers_url":"https://api.github.com/users/dhis2/followers","following_url":"https://api.github.com/users/dhis2/following{/other_user}","gists_url":"https://api.github.com/users/dhis2/gists{/gist_id}","starred_url":"https://api.github.com/users/dhis2/starred{/owner}{/repo}","subscriptions_url":"https://api.github.com/users/dhis2/subscriptions","organizations_url":"https://api.github.com/users/dhis2/orgs","repos_url":"https://api.github.com/users/dhis2/repos","events_url":"https://api.github.com/users/dhis2/events{/privacy}","received_events_url":"https://api.github.com/users/dhis2/received_events","type":"Organization","site_admin":false},"html_url":"https://github.com/dhis2/dhis2-core","description":"DHIS2 Core. Written in Java. Contains the service layer and Web API.","fork":false,"url":"https://api.github.com/repos/dhis2/dhis2-core","forks_url":"https://api.github.com/repos/dhis2/dhis2-core/forks","keys_url":"https://api.github.com/repos/dhis2/dhis2-core/keys{/key_id}","collaborators_url":"https://api.github.com/repos/dhis2/dhis2-core/collaborators{/collaborator}","teams_url":"https://api.github.com/repos/dhis2/dhis2-core/teams","hooks_url":"https://api.github.com/repos/dhis2/dhis2-core/hooks","issue_events_url":"https://api.github.com/repos/dhis2/dhis2-core/issues/events{/number}","events_url":"https://api.github.com/repos/dhis2/dhis2-core/events","assignees_url":"https://api.github.com/repos/dhis2/dhis2-core/assignees{/user}","branches_url":"https://api.github.com/repos/dhis2/dhis2-core/branches{/branch}","tags_url":"https://api.github.com/repos/dhis2/dhis2-core/tags","blobs_url":"https://api.github.com/repos/dhis2/dhis2-core/git/blobs{/sha}","git_tags_url":"https://api.github.com/repos/dhis2/dhis2-core/git/tags{/sha}","git_refs_url":"https://api.github.com/repos/dhis2/dhis2-core/git/refs{/sha}","trees_url":"https://api.github.com/repos/dhis2/dhis2-core/git/trees{/sha}","statuses_url":"https://api.github.com/repos/dhis2/dhis2-core/statuses/{sha}","languages_url":"https://api.github.com/repos/dhis2/dhis2-core/languages","stargazers_url":"https://api.github.com/repos/dhis2/dhis2-core/stargazers","contributors_url":"https://api.github.com/repos/dhis2/dhis2-core/contributors","subscribers_url":"https://api.github.com/repos/dhis2/dhis2-core/subscribers","subscription_url":"https://api.github.com/repos/dhis2/dhis2-core/subscription","commits_url":"https://api.github.com/repos/dhis2/dhis2-core/commits{/sha}","git_commits_url":"https://api.github.com/repos/dhis2/dhis2-core/git/commits{/sha}","comments_url":"https://api.github.com/repos/dhis2/dhis2-core/comments{/number}","issue_comment_url":"https://api.github.com/repos/dhis2/dhis2-core/issues/comments{/number}","contents_url":"https://api.github.com/repos/dhis2/dhis2-core/contents/{+path}","compare_url":"https://api.github.com/repos/dhis2/dhis2-core/compare/{base}...{head}","merges_url":"https://api.github.com/repos/dhis2/dhis2-core/merges","archive_url":"https://api.github.com/repos/dhis2/dhis2-core/{archive_format}{/ref}","downloads_url":"https://api.github.com/repos/dhis2/dhis2-core/downloads","issues_url":"https://api.github.com/repos/dhis2/dhis2-core/issues{/number}","pulls_url":"https://api.github.com/repos/dhis2/dhis2-core/pulls{/number}","milestones_url":"https://api.github.com/repos/dhis2/dhis2-core/milestones{/number}","notifications_url":"https://api.github.com/repos/dhis2/dhis2-core/notifications{?since,all,participating}","labels_url":"https://api.github.com/repos/dhis2/dhis2-core/labels{/name}","releases_url":"https://api.github.com/repos/dhis2/dhis2-core/releases{/id}","deployments_url":"https://api.github.com/repos/dhis2/dhis2-core/deployments"},"head_repository":{"id":66940520,"node_id":"MDEwOlJlcG9zaXRvcnk2Njk0MDUyMA==","name":"dhis2-core","full_name":"dhis2/dhis2-core","private":false,"owner":{"login":"dhis2","id":1089987,"node_id":"MDEyOk9yZ2FuaXphdGlvbjEwODk5ODc=","avatar_url":"https://avatars.githubusercontent.com/u/1089987?v=4","gravatar_id":"","url":"https://api.github.com/users/dhis2","html_url":"https://github.com/dhis2","followers_url":"https://api.github.com/users/dhis2/followers","following_url":"https://api.github.com/users/dhis2/following{/other_user}","gists_url":"https://api.github.com/users/dhis2/gists{/gist_id}","starred_url":"https://api.github.com/users/dhis2/starred{/owner}{/repo}","subscriptions_url":"https://api.github.com/users/dhis2/subscriptions","organizations_url":"https://api.github.com/users/dhis2/orgs","repos_url":"https://api.github.com/users/dhis2/repos","events_url":"https://api.github.com/users/dhis2/events{/privacy}","received_events_url":"https://api.github.com/users/dhis2/received_events","type":"Organization","site_admin":false},"html_url":"https://github.com/dhis2/dhis2-core","description":"DHIS2 Core. Written in Java. Contains the service layer and Web API.","fork":false,"url":"https://api.github.com/repos/dhis2/dhis2-core","forks_url":"https://api.github.com/repos/dhis2/dhis2-core/forks","keys_url":"https://api.github.com/repos/dhis2/dhis2-core/keys{/key_id}","collaborators_url":"https://api.github.com/repos/dhis2/dhis2-core/collaborators{/collaborator}","teams_url":"https://api.github.com/repos/dhis2/dhis2-core/teams","hooks_url":"https://api.github.com/repos/dhis2/dhis2-core/hooks","issue_events_url":"https://api.github.com/repos/dhis2/dhis2-core/issues/events{/number}","events_url":"https://api.github.com/repos/dhis2/dhis2-core/events","assignees_url":"https://api.github.com/repos/dhis2/dhis2-core/assignees{/user}","branches_url":"https://api.github.com/repos/dhis2/dhis2-core/branches{/branch}","tags_url":"https://api.github.com/repos/dhis2/dhis2-core/tags","blobs_url":"https://api.github.com/repos/dhis2/dhis2-core/git/blobs{/sha}","git_tags_url":"https://api.github.com/repos/dhis2/dhis2-core/git/tags{/sha}","git_refs_url":"https://api.github.com/repos/dhis2/dhis2-core/git/refs{/sha}","trees_url":"https://api.github.com/repos/dhis2/dhis2-core/git/trees{/sha}","statuses_url":"https://api.github.com/repos/dhis2/dhis2-core/statuses/{sha}","languages_url":"https://api.github.com/repos/dhis2/dhis2-core/languages","stargazers_url":"https://api.github.com/repos/dhis2/dhis2-core/stargazers","contributors_url":"https://api.github.com/repos/dhis2/dhis2-core/contributors","subscribers_url":"https://api.github.com/repos/dhis2/dhis2-core/subscribers","subscription_url":"https://api.github.com/repos/dhis2/dhis2-core/subscription","commits_url":"https://api.github.com/repos/dhis2/dhis2-core/commits{/sha}","git_commits_url":"https://api.github.com/repos/dhis2/dhis2-core/git/commits{/sha}","comments_url":"https://api.github.com/repos/dhis2/dhis2-core/comments{/number}","issue_comment_url":"https://api.github.com/repos/dhis2/dhis2-core/issues/comments{/number}","contents_url":"https://api.github.com/repos/dhis2/dhis2-core/contents/{+path}","compare_url":"https://api.github.com/repos/dhis2/dhis2-core/compare/{base}...{head}","merges_url":"https://api.github.com/repos/dhis2/dhis2-core/merges","archive_url":"https://api.github.com/repos/dhis2/dhis2-core/{archive_format}{/ref}","downloads_url":"https://api.github.com/repos/dhis2/dhis2-core/downloads","issues_url":"https://api.github.com/repos/dhis2/dhis2-core/issues{/number}","pulls_url":"https://api.github.com/repos/dhis2/dhis2-core/pulls{/number}","milestones_url":"https://api.github.com/repos/dhis2/dhis2-core/milestones{/number}","notifications_url":"https://api.github.com/repos/dhis2/dhis2-core/notifications{?since,all,participating}","labels_url":"https://api.github.com/repos/dhis2/dhis2-core/labels{/name}","releases_url":"https://api.github.com/repos/dhis2/dhis2-core/releases{/id}","deployments_url":"https://api.github.com/repos/dhis2/dhis2-core/deployments"}}