{"total_count":2,"jobs":[{"id":3655890337,"run_id":1254966675,"run_url":"https://api.github.com/repos/dhis2/dhis2-core/actions/runs/1254966675","run_attempt":1,"node_id":"CR_kwDOA_1uaM7Z6HWh","head_sha":"6f45844ca254b910bdfe4bf54a39bd0190d0354a","url":"https://api.github.com/repos/dhis2/dhis2-core/actions/jobs/3655890337","html_url":"https://github.com/dhis2/dhis2-core/runs/3655890337?check_suite_focus=true","status":"completed","conclusion":"success","started_at":"2021-09-20T19:55:44Z","completed_at":"2021-09-20T20:12:25Z","name":"unit-test","steps":[{"name":"Set up job","status":"completed","conclusion":"success","number":1,"started_at":"2021-09-20T21:55:44.000+02:00","completed_at":"2021-09-20T21:55:46.000+02:00"},{"name":"Run actions/checkout@v2","status":"completed","conclusion":"success","number":2,"started_at":"2021-09-20T21:55:46.000+02:00","completed_at":"2021-09-20T21:55:50.000+02:00"},{"name":"Set up JDK 11","status":"completed","conclusion":"success","number":3,"started_at":"2021-09-20T21:55:50.000+02:00","completed_at":"2021-09-20T21:55:56.000+02:00"},{"name":"Cache maven artifacts","status":"completed","conclusion":"success","number":4,"started_at":"2021-09-20T21:55:56.000+02:00","completed_at":"2021-09-20T21:56:16.000+02:00"},{"name":"Test core","status":"completed","conclusion":"success","number":5,"started_at":"2021-09-20T21:56:16.000+02:00","completed_at":"2021-09-20T22:10:55.000+02:00"},{"name":"Test dhis-web","status":"completed","conclusion":"success","number":6,"started_at":"2021-09-20T22:10:55.000+02:00","completed_at":"2021-09-20T22:12:24.000+02:00"},{"name":"Post Cache maven artifacts","status":"completed","conclusion":"success","number":10,"started_at":"2021-09-20T22:12:24.000+02:00","completed_at":"2021-09-20T22:12:25.000+02:00"},{"name":"Post Set up JDK 11","status":"completed","conclusion":"success","number":11,"started_at":"2021-09-20T22:12:25.000+02:00","completed_at":"2021-09-20T22:12:25.000+02:00"},{"name":"Post Run actions/checkout@v2","status":"completed","conclusion":"success","number":12,"started_at":"2021-09-20T22:12:25.000+02:00","completed_at":"2021-09-20T22:12:25.000+02:00"},{"name":"Complete job","status":"completed","conclusion":"success","number":13,"started_at":"2021-09-20T22:12:25.000+02:00","completed_at":"2021-09-20T22:12:25.000+02:00"}],"check_run_url":"https://api.github.com/repos/dhis2/dhis2-core/check-runs/3655890337","labels":["ubuntu-latest"],"runner_id":3,"runner_name":"GitHub Actions 3","runner_group_id":2,"runner_group_name":"GitHub Actions"},{"id":3655890424,"run_id":1254966675,"run_url":"https://api.github.com/repos/dhis2/dhis2-core/actions/runs/1254966675","run_attempt":1,"node_id":"CR_kwDOA_1uaM7Z6HX4","head_sha":"6f45844ca254b910bdfe4bf54a39bd0190d0354a","url":"https://api.github.com/repos/dhis2/dhis2-core/actions/jobs/3655890424","html_url":"https://github.com/dhis2/dhis2-core/runs/3655890424?check_suite_focus=true","status":"completed","conclusion":"success","started_at":"2021-09-20T19:55:44Z","completed_at":"2021-09-20T20:16:38Z","name":"integration-test","steps":[{"name":"Set up job","status":"completed","conclusion":"success","number":1,"started_at":"2021-09-20T21:55:44.000+02:00","completed_at":"2021-09-20T21:55:46.000+02:00"},{"name":"Run actions/checkout@v2","status":"completed","conclusion":"success","number":2,"started_at":"2021-09-20T21:55:46.000+02:00","completed_at":"2021-09-20T21:55:50.000+02:00"},{"name":"Set up JDK 11","status":"completed","conclusion":"success","number":3,"started_at":"2021-09-20T21:55:50.000+02:00","completed_at":"2021-09-20T21:55:55.000+02:00"},{"name":"Cache maven artifacts","status":"completed","conclusion":"success","number":4,"started_at":"2021-09-20T21:55:55.000+02:00","completed_at":"2021-09-20T21:56:17.000+02:00"},{"name":"Run integration tests","status":"completed","conclusion":"success","number":5,"started_at":"2021-09-20T21:56:17.000+02:00","completed_at":"2021-09-20T22:16:38.000+02:00"},{"name":"Post Cache maven artifacts","status":"completed","conclusion":"success","number":8,"started_at":"2021-09-20T22:16:38.000+02:00","completed_at":"2021-09-20T22:16:38.000+02:00"},{"name":"Post Set up JDK 11","status":"completed","conclusion":"success","number":9,"started_at":"2021-09-20T22:16:38.000+02:00","completed_at":"2021-09-20T22:16:38.000+02:00"},{"name":"Post Run actions/checkout@v2","status":"completed","conclusion":"success","number":10,"started_at":"2021-09-20T22:16:38.000+02:00","completed_at":"2021-09-20T22:16:38.000+02:00"},{"name":"Complete job","status":"completed","conclusion":"success","number":11,"started_at":"2021-09-20T22:16:38.000+02:00","completed_at":"2021-09-20T22:16:38.000+02:00"}],"check_run_url":"https://api.github.com/repos/dhis2/dhis2-core/check-runs/3655890424","labels":["ubuntu-latest"],"runner_id":5,"runner_name":"GitHub Actions 5","runner_group_id":2,"runner_group_name":"GitHub Actions"}]}