{"total_count":2,"jobs":[{"id":3733665110,"run_id":1282986645,"run_url":"https://api.github.com/repos/dhis2/dhis2-core/actions/runs/1282986645","run_attempt":1,"node_id":"CR_kwDOA_1uaM7eizVW","head_sha":"06b62266f642f514bc9f0eb8f625579d79bb1487","url":"https://api.github.com/repos/dhis2/dhis2-core/actions/jobs/3733665110","html_url":"https://github.com/dhis2/dhis2-core/runs/3733665110?check_suite_focus=true","status":"completed","conclusion":"success","started_at":"2021-09-28T14:20:23Z","completed_at":"2021-09-28T14:41:33Z","name":"integration-test","steps":[{"name":"Set up job","status":"completed","conclusion":"success","number":1,"started_at":"2021-09-28T16:20:23.000+02:00","completed_at":"2021-09-28T16:20:26.000+02:00"},{"name":"Run actions/checkout@v2","status":"completed","conclusion":"success","number":2,"started_at":"2021-09-28T16:20:26.000+02:00","completed_at":"2021-09-28T16:20:30.000+02:00"},{"name":"Set up JDK 11","status":"completed","conclusion":"success","number":3,"started_at":"2021-09-28T16:20:30.000+02:00","completed_at":"2021-09-28T16:20:36.000+02:00"},{"name":"Cache maven artifacts","status":"completed","conclusion":"success","number":4,"started_at":"2021-09-28T16:20:36.000+02:00","completed_at":"2021-09-28T16:20:57.000+02:00"},{"name":"Run integration tests","status":"completed","conclusion":"success","number":5,"started_at":"2021-09-28T16:20:57.000+02:00","completed_at":"2021-09-28T16:41:32.000+02:00"},{"name":"Post Cache maven artifacts","status":"completed","conclusion":"success","number":8,"started_at":"2021-09-28T16:41:32.000+02:00","completed_at":"2021-09-28T16:41:33.000+02:00"},{"name":"Post Set up JDK 11","status":"completed","conclusion":"success","number":9,"started_at":"2021-09-28T16:41:33.000+02:00","completed_at":"2021-09-28T16:41:33.000+02:00"},{"name":"Post Run actions/checkout@v2","status":"completed","conclusion":"success","number":10,"started_at":"2021-09-28T16:41:33.000+02:00","completed_at":"2021-09-28T16:41:33.000+02:00"},{"name":"Complete job","status":"completed","conclusion":"success","number":11,"started_at":"2021-09-28T16:41:33.000+02:00","completed_at":"2021-09-28T16:41:33.000+02:00"}],"check_run_url":"https://api.github.com/repos/dhis2/dhis2-core/check-runs/3733665110","labels":["ubuntu-latest"],"runner_id":10,"runner_name":"GitHub Actions 10","runner_group_id":2,"runner_group_name":"GitHub Actions"},{"id":3733665239,"run_id":1282986645,"run_url":"https://api.github.com/repos/dhis2/dhis2-core/actions/runs/1282986645","run_attempt":1,"node_id":"CR_kwDOA_1uaM7eizXX","head_sha":"06b62266f642f514bc9f0eb8f625579d79bb1487","url":"https://api.github.com/repos/dhis2/dhis2-core/actions/jobs/3733665239","html_url":"https://github.com/dhis2/dhis2-core/runs/3733665239?check_suite_focus=true","status":"completed","conclusion":"success","started_at":"2021-09-28T14:20:24Z","completed_at":"2021-09-28T14:38:11Z","name":"unit-test","steps":[{"name":"Set up job","status":"completed","conclusion":"success","number":1,"started_at":"2021-09-28T16:20:24.000+02:00","completed_at":"2021-09-28T16:20:27.000+02:00"},{"name":"Run actions/checkout@v2","status":"completed","conclusion":"success","number":2,"started_at":"2021-09-28T16:20:27.000+02:00","completed_at":"2021-09-28T16:20:31.000+02:00"},{"name":"Set up JDK 11","status":"completed","conclusion":"success","number":3,"started_at":"2021-09-28T16:20:31.000+02:00","completed_at":"2021-09-28T16:20:37.000+02:00"},{"name":"Cache maven artifacts","status":"completed","conclusion":"success","number":4,"started_at":"2021-09-28T16:20:37.000+02:00","completed_at":"2021-09-28T16:20:57.000+02:00"},{"name":"Test core","status":"completed","conclusion":"success","number":5,"started_at":"2021-09-28T16:20:57.000+02:00","completed_at":"2021-09-28T16:36:34.000+02:00"},{"name":"Test dhis-web","status":"completed","conclusion":"success","number":6,"started_at":"2021-09-28T16:36:34.000+02:00","completed_at":"2021-09-28T16:38:10.000+02:00"},{"name":"Post Cache maven artifacts","status":"completed","conclusion":"success","number":10,"started_at":"2021-09-28T16:38:10.000+02:00","completed_at":"2021-09-28T16:38:11.000+02:00"},{"name":"Post Set up JDK 11","status":"completed","conclusion":"success","number":11,"started_at":"2021-09-28T16:38:11.000+02:00","completed_at":"2021-09-28T16:38:11.000+02:00"},{"name":"Post Run actions/checkout@v2","status":"completed","conclusion":"success","number":12,"started_at":"2021-09-28T16:38:11.000+02:00","completed_at":"2021-09-28T16:38:11.000+02:00"},{"name":"Complete job","status":"completed","conclusion":"success","number":13,"started_at":"2021-09-28T16:38:11.000+02:00","completed_at":"2021-09-28T16:38:11.000+02:00"}],"check_run_url":"https://api.github.com/repos/dhis2/dhis2-core/check-runs/3733665239","labels":["ubuntu-latest"],"runner_id":12,"runner_name":"GitHub Actions 12","runner_group_id":2,"runner_group_name":"GitHub Actions"}]}