{"total_count":2,"jobs":[{"id":3788513504,"run_id":1302807764,"run_url":"https://api.github.com/repos/dhis2/dhis2-core/actions/runs/1302807764","run_attempt":1,"node_id":"CR_kwDOA_1uaM7h0CDg","head_sha":"a1f8d94ce4d6cdfc9ec9d5aeec2f8875c559def9","url":"https://api.github.com/repos/dhis2/dhis2-core/actions/jobs/3788513504","html_url":"https://github.com/dhis2/dhis2-core/runs/3788513504?check_suite_focus=true","status":"completed","conclusion":"failure","started_at":"2021-10-04T08:41:49Z","completed_at":"2021-10-04T08:59:44Z","name":"integration-test","steps":[{"name":"Set up job","status":"completed","conclusion":"success","number":1,"started_at":"2021-10-04T10:41:49.000+02:00","completed_at":"2021-10-04T10:41:52.000+02:00"},{"name":"Run actions/checkout@v2","status":"completed","conclusion":"success","number":2,"started_at":"2021-10-04T10:41:52.000+02:00","completed_at":"2021-10-04T10:41:56.000+02:00"},{"name":"Set up JDK 11","status":"completed","conclusion":"success","number":3,"started_at":"2021-10-04T10:41:56.000+02:00","completed_at":"2021-10-04T10:42:01.000+02:00"},{"name":"Cache maven artifacts","status":"completed","conclusion":"success","number":4,"started_at":"2021-10-04T10:42:01.000+02:00","completed_at":"2021-10-04T10:42:19.000+02:00"},{"name":"Run integration tests","status":"completed","conclusion":"failure","number":5,"started_at":"2021-10-04T10:42:19.000+02:00","completed_at":"2021-10-04T10:59:44.000+02:00"},{"name":"Post Cache maven artifacts","status":"completed","conclusion":"skipped","number":8,"started_at":"2021-10-04T10:59:44.000+02:00","completed_at":"2021-10-04T10:59:44.000+02:00"},{"name":"Post Set up JDK 11","status":"completed","conclusion":"success","number":9,"started_at":"2021-10-04T10:59:44.000+02:00","completed_at":"2021-10-04T10:59:44.000+02:00"},{"name":"Post Run actions/checkout@v2","status":"completed","conclusion":"success","number":10,"started_at":"2021-10-04T10:59:44.000+02:00","completed_at":"2021-10-04T10:59:44.000+02:00"},{"name":"Complete job","status":"completed","conclusion":"success","number":11,"started_at":"2021-10-04T10:59:44.000+02:00","completed_at":"2021-10-04T10:59:44.000+02:00"}],"check_run_url":"https://api.github.com/repos/dhis2/dhis2-core/check-runs/3788513504","labels":["ubuntu-latest"],"runner_id":12,"runner_name":"GitHub Actions 12","runner_group_id":2,"runner_group_name":"GitHub Actions"},{"id":3788513566,"run_id":1302807764,"run_url":"https://api.github.com/repos/dhis2/dhis2-core/actions/runs/1302807764","run_attempt":1,"node_id":"CR_kwDOA_1uaM7h0CEe","head_sha":"a1f8d94ce4d6cdfc9ec9d5aeec2f8875c559def9","url":"https://api.github.com/repos/dhis2/dhis2-core/actions/jobs/3788513566","html_url":"https://github.com/dhis2/dhis2-core/runs/3788513566?check_suite_focus=true","status":"completed","conclusion":"failure","started_at":"2021-10-04T08:41:49Z","completed_at":"2021-10-04T08:57:51Z","name":"unit-test","steps":[{"name":"Set up job","status":"completed","conclusion":"success","number":1,"started_at":"2021-10-04T10:41:49.000+02:00","completed_at":"2021-10-04T10:41:52.000+02:00"},{"name":"Run actions/checkout@v2","status":"completed","conclusion":"success","number":2,"started_at":"2021-10-04T10:41:52.000+02:00","completed_at":"2021-10-04T10:41:57.000+02:00"},{"name":"Set up JDK 11","status":"completed","conclusion":"success","number":3,"started_at":"2021-10-04T10:41:57.000+02:00","completed_at":"2021-10-04T10:42:02.000+02:00"},{"name":"Cache maven artifacts","status":"completed","conclusion":"success","number":4,"started_at":"2021-10-04T10:42:02.000+02:00","completed_at":"2021-10-04T10:42:23.000+02:00"},{"name":"Test core","status":"completed","conclusion":"failure","number":5,"started_at":"2021-10-04T10:42:23.000+02:00","completed_at":"2021-10-04T10:57:51.000+02:00"},{"name":"Test dhis-web","status":"completed","conclusion":"skipped","number":6,"started_at":"2021-10-04T10:57:51.000+02:00","completed_at":"2021-10-04T10:57:51.000+02:00"},{"name":"Post Cache maven artifacts","status":"completed","conclusion":"skipped","number":10,"started_at":"2021-10-04T10:57:51.000+02:00","completed_at":"2021-10-04T10:57:51.000+02:00"},{"name":"Post Set up JDK 11","status":"completed","conclusion":"success","number":11,"started_at":"2021-10-04T10:57:51.000+02:00","completed_at":"2021-10-04T10:57:51.000+02:00"},{"name":"Post Run actions/checkout@v2","status":"completed","conclusion":"success","number":12,"started_at":"2021-10-04T10:57:51.000+02:00","completed_at":"2021-10-04T10:57:51.000+02:00"},{"name":"Complete job","status":"completed","conclusion":"success","number":13,"started_at":"2021-10-04T10:57:51.000+02:00","completed_at":"2021-10-04T10:57:51.000+02:00"}],"check_run_url":"https://api.github.com/repos/dhis2/dhis2-core/check-runs/3788513566","labels":["ubuntu-latest"],"runner_id":13,"runner_name":"GitHub Actions 13","runner_group_id":2,"runner_group_name":"GitHub Actions"}]}